human_randgen/__init__.py
human_randgen/model.py
human_randgen-1.0.2.dist-info/LICENSE
human_randgen-1.0.2.dist-info/METADATA
human_randgen-1.0.2.dist-info/WHEEL
human_randgen-1.0.2.dist-info/top_level.txt
human_randgen-1.0.2.dist-info/RECORD
