Metadata-Version: 2.1
Name: human-randgen
Version: 1.0.2
Summary: A random generator for simulating human response times
Author-email: rzqx <rzqx@pm.me>
License: MIT License        
Project-URL: Homepage, https://github.com/rzqx/human_randgen
Project-URL: Bug Tracker, https://github.com/rzqx/human_randgen/issues
Classifier: Programming Language :: Python :: 3
Classifier: License :: OSI Approved :: MIT License
Classifier: Operating System :: OS Independent
Requires-Python: >=3.7
License-File: LICENSE
